cvx_package_template/__init__.py
cvx_package_template/hello_world.py
cvx_package_template-0.1.3.dist-info/METADATA
cvx_package_template-0.1.3.dist-info/WHEEL
cvx_package_template-0.1.3.dist-info/licenses/LICENSE
cvx_package_template-0.1.3.dist-info/RECORD
