Metadata-Version: 2.4
Name: cvx-package-template
Version: 0.1.3
Summary: CVX package template for convex optimization projects.
Project-URL: Homepage, https://github.com/langestefan/cvx-package-template
Project-URL: Repository, https://github.com/langestefan/cvx-package-template.git
Project-URL: Documentation, https://github.com/langestefan/cvx-package-template
Project-URL: Bug Tracker, https://github.com/langestefan/cvx-package-template/issues
Author: Author 1, Author 2
Maintainer-email: My Name <myname@place.com>
License: MIT
License-File: LICENSE
Keywords: convex optimization,cvxpy,mathematical programming
Classifier: Development Status :: 4 - Beta
Classifier: Intended Audience :: Developers
Classifier: Intended Audience :: Science/Research
Classifier: License :: OSI Approved :: Apache Software License
Classifier: Operating System :: OS Independent
Classifier: Programming Language :: Python :: 3
Classifier: Programming Language :: Python :: 3.12
Classifier: Programming Language :: Python :: 3.13
Classifier: Topic :: Scientific/Engineering :: Artificial Intelligence
Classifier: Topic :: Scientific/Engineering :: Mathematics
Classifier: Topic :: Software Development :: Libraries :: Python Modules
Requires-Python: >=3.12
Requires-Dist: cvxpy>=1.7.1
